download_google_images/__init__.py
download_google_images/chromedriver.exe
download_google_images/main.py
download_google_images-0.1.0.dist-info/entry_points.txt
download_google_images-0.1.0.dist-info/WHEEL
download_google_images-0.1.0.dist-info/METADATA
download_google_images-0.1.0.dist-info/RECORD
