Metadata-Version: 2.1
Name: download-google-images
Version: 0.1.0
Summary: 
Author: Adarsh1999
Author-email: adarshguptamaurya@gmail.com
Requires-Python: >=3.7,<4.0
Classifier: Programming Language :: Python :: 3
Classifier: Programming Language :: Python :: 3.7
Classifier: Programming Language :: Python :: 3.8
Requires-Dist: pillow (>=7.1.1,<8.0.0)
Requires-Dist: requests (>=2.23.0,<3.0.0)
Requires-Dist: selenium (>=3.141.0,<4.0.0)
Requires-Dist: typer[all] (>=0.1.1,<0.2.0)
